bilifm-0.2.7.dist-info/METADATA
bilifm-0.2.7.dist-info/WHEEL
bilifm-0.2.7.dist-info/entry_points.txt
bilifm-0.2.7.dist-info/licenses/LICENSE
bilifm/__init__.py
bilifm/__main__.py
bilifm/__version__.py
bilifm/audio.py
bilifm/command.py
bilifm/fav.py
bilifm/season.py
bilifm/series.py
bilifm/test.py
bilifm/tui.py
bilifm/user.py
bilifm/util.py
bilifm-0.2.7.dist-info/RECORD
