Metadata-Version: 2.1
Name: bilifm
Version: 0.2.7
Summary: Download Bilibili videos as audios.
Author-Email: jingfelix <jingfelix@outlook.com>, Felix Jing <jingfelix@outlook.com>
License: GPLv3
Classifier: License :: OSI Approved :: GNU General Public License v3 (GPLv3)
Classifier: Operating System :: OS Independent
Classifier: Programming Language :: Python :: 3
Project-URL: Homepage, https://github.com/jingfelix/bilifm
Project-URL: Bug Tracker, https://github.com/jingfelix/bilifm/issues
Requires-Python: >=3.10
Requires-Dist: requests>=2.32.4
Requires-Dist: typer[all]>=0.9.0
